greenback/__init__.py
greenback/_impl.py
greenback/_util.py
greenback/_version.py
greenback/py.typed
greenback/_tests/__init__.py
greenback/_tests/conftest.py
greenback/_tests/test_impl.py
greenback/_tests/test_util.py
greenback-1.2.0.dist-info/LICENSE
greenback-1.2.0.dist-info/LICENSE.APACHE2
greenback-1.2.0.dist-info/LICENSE.MIT
greenback-1.2.0.dist-info/METADATA
greenback-1.2.0.dist-info/WHEEL
greenback-1.2.0.dist-info/top_level.txt
greenback-1.2.0.dist-info/RECORD
