Metadata-Version: 2.1
Name: greenback
Version: 1.2.0
Summary: Reenter an async event loop from synchronous code
Home-page: https://github.com/oremanj/greenback
Author: Joshua Oreman
Author-email: oremanj@gmail.com
License: MIT -or- Apache License 2.0
Keywords: async,io,trio,asyncio
Classifier: License :: OSI Approved :: MIT License
Classifier: License :: OSI Approved :: Apache Software License
Classifier: Framework :: Trio
Classifier: Framework :: AsyncIO
Classifier: Operating System :: POSIX :: Linux
Classifier: Operating System :: MacOS :: MacOS X
Classifier: Operating System :: Microsoft :: Windows
Classifier: Programming Language :: Python :: 3 :: Only
Classifier: Programming Language :: Python :: Implementation :: CPython
Classifier: Programming Language :: Python :: Implementation :: PyPy
Classifier: Development Status :: 4 - Beta
Requires-Python: >=3.8
License-File: LICENSE
License-File: LICENSE.APACHE2
License-File: LICENSE.MIT
Requires-Dist: greenlet !=0.4.17
Requires-Dist: sniffio
Requires-Dist: outcome
